optimus/__init__.py
optimus/agg.py
optimus/audf.py
optimus/bumblebee.py
optimus/enricher.py
optimus/infer.py
optimus/optimus.py
optimus/spark.py
optimus/version.py
optimus/css/__init__.py
optimus/css/styles.css
optimus/dataframe/__init__.py
optimus/dataframe/columns.py
optimus/dataframe/create.py
optimus/dataframe/extension.py
optimus/dataframe/rows.py
optimus/dataframe/plots/__init__.py
optimus/dataframe/plots/functions.py
optimus/dataframe/plots/plots.py
optimus/dl/__init__.py
optimus/dl/models.py
optimus/helpers/__init__.py
optimus/helpers/check.py
optimus/helpers/columns.py
optimus/helpers/columns_expression.py
optimus/helpers/constants.py
optimus/helpers/converter.py
optimus/helpers/debug.py
optimus/helpers/decorators.py
optimus/helpers/filters.py
optimus/helpers/functions.py
optimus/helpers/json.py
optimus/helpers/logger.py
optimus/helpers/output.py
optimus/helpers/parser.py
optimus/helpers/pickle.py
optimus/helpers/raiseit.py
optimus/helpers/test.py
optimus/io/__init__.py
optimus/io/abstract_driver.py
optimus/io/cassandra.py
optimus/io/driver_context.py
optimus/io/factory.py
optimus/io/jdbc.py
optimus/io/load.py
optimus/io/mysql.py
optimus/io/oracle.py
optimus/io/postgresql.py
optimus/io/presto.py
optimus/io/properties.py
optimus/io/redis.py
optimus/io/redshift.py
optimus/io/save.py
optimus/io/sqlite.py
optimus/io/sqlserver.py
optimus/jars/RedshiftJDBC42-1.2.16.1027.jar
optimus/jars/mssql-jdbc-7.4.1.jre8.jar
optimus/jars/mysql-connector-java-8.0.16.jar
optimus/jars/ojdbc10.jar
optimus/jars/ojdbc8.jar
optimus/jars/postgresql-42.2.5.jar
optimus/jars/presto-jdbc-0.224.jar
optimus/jars/spark-cassandra-connector_2.11-2.4.1.jar
optimus/jars/spark-redis-2.4.1-SNAPSHOT-jar-with-dependencies.jar
optimus/jars/sqlite-jdbc-3.27.2.1.jar
optimus/ml/__init__.py
optimus/ml/contants.py
optimus/ml/distancecluster.py
optimus/ml/encoding.py
optimus/ml/keycollision.py
optimus/ml/models.py
optimus/ml/pipelines.py
optimus/outliers/__init__.py
optimuspyspark-2.2.32.dist-info/LICENSE
optimuspyspark-2.2.32.dist-info/METADATA
optimuspyspark-2.2.32.dist-info/WHEEL
optimuspyspark-2.2.32.dist-info/top_level.txt
optimuspyspark-2.2.32.dist-info/RECORD
