Metadata-Version: 2.1
Name: optimuspyspark
Version: 2.2.32
Summary: Optimus is the missing framework for cleaning and pre-processing data in a distributed fashion with pyspark.
Home-page: https://github.com/ironmussa/Optimus/
Author: Favio Vazquez and Argenis Leon
Author-email: argenisleon@gmail.com
License: APACHE
Download-URL: https://github.com/ironmussa/Optimus/archive/2.2.32.tar.gz
Keywords: datacleaner,apachespark,spark,pyspark,data-wrangling,data-cleansing,data-profiling
Platform: UNKNOWN
Classifier: Development Status :: 5 - Production/Stable
Classifier: Intended Audience :: Developers
Classifier: Topic :: Scientific/Engineering :: Artificial Intelligence
Classifier: License :: OSI Approved :: Apache Software License
Classifier: Programming Language :: Python :: 3.5
Classifier: Programming Language :: Python :: 3.6
Requires-Dist: simplejson (==3.16.0)
Requires-Dist: cryptography (==2.7)
Requires-Dist: imgkit (==1.0.1)
Requires-Dist: packaging (==19.0)
Requires-Dist: requests (==2.20.0)
Requires-Dist: tqdm (==4.28.1)
Requires-Dist: pymongo (==3.9.0)
Requires-Dist: fastnumbers (==2.2.1)
Requires-Dist: multipledispatch (==0.6.0)
Requires-Dist: numpy (==1.17.2)
Requires-Dist: matplotlib (==3.0.3)
Requires-Dist: pyspark (==2.4.1)
Requires-Dist: findspark (==1.3.0)
Requires-Dist: seaborn (==0.9.0)
Requires-Dist: deprecated (==1.2.5)
Requires-Dist: setuptools (==41.6.0)
Requires-Dist: pyarrow (==0.13.0)
Requires-Dist: Jinja2 (==2.10.1)
Requires-Dist: tensorflow (==1.13.1)
Requires-Dist: keras (==2.2.4)
Requires-Dist: pygments (>=2.2.0)
Requires-Dist: flask (==1.0.2)
Requires-Dist: ipython (==7.5.0)
Requires-Dist: ratelimit (==2.2.1)
Requires-Dist: humanize (==0.5.1)
Requires-Dist: h2o-pysparkling-2.4 (==2.4.10)
Requires-Dist: psutil (==5.7.2)
Requires-Dist: backoff (==1.10.0)
Requires-Dist: kombu (==4.6.1)
Requires-Dist: pandas (==0.24.2)
Requires-Dist: ordered-set (==3.1.1)
Requires-Dist: deepdiff (==4.0.6)
Requires-Dist: pypika (==0.32.0)
Requires-Dist: statsmodels (==0.10.1)
Requires-Dist: glom (==19.10.0)
Requires-Dist: singleton-decorator (==1.0.0)
Requires-Dist: nltk (==3.4.5)
Provides-Extra: all
Requires-Dist: simplejson (==3.16.0) ; extra == 'all'
Requires-Dist: cryptography (==2.7) ; extra == 'all'
Requires-Dist: imgkit (==1.0.1) ; extra == 'all'
Requires-Dist: packaging (==19.0) ; extra == 'all'
Requires-Dist: requests (==2.20.0) ; extra == 'all'
Requires-Dist: tqdm (==4.28.1) ; extra == 'all'
Requires-Dist: pymongo (==3.9.0) ; extra == 'all'
Requires-Dist: fastnumbers (==2.2.1) ; extra == 'all'
Requires-Dist: multipledispatch (==0.6.0) ; extra == 'all'
Requires-Dist: numpy (==1.17.2) ; extra == 'all'
Requires-Dist: matplotlib (==3.0.3) ; extra == 'all'
Requires-Dist: pyspark (==2.4.1) ; extra == 'all'
Requires-Dist: findspark (==1.3.0) ; extra == 'all'
Requires-Dist: seaborn (==0.9.0) ; extra == 'all'
Requires-Dist: deprecated (==1.2.5) ; extra == 'all'
Requires-Dist: setuptools (==41.6.0) ; extra == 'all'
Requires-Dist: pyarrow (==0.13.0) ; extra == 'all'
Requires-Dist: Jinja2 (==2.10.1) ; extra == 'all'
Requires-Dist: tensorflow (==1.13.1) ; extra == 'all'
Requires-Dist: keras (==2.2.4) ; extra == 'all'
Requires-Dist: pygments (>=2.2.0) ; extra == 'all'
Requires-Dist: flask (==1.0.2) ; extra == 'all'
Requires-Dist: ipython (==7.5.0) ; extra == 'all'
Requires-Dist: ratelimit (==2.2.1) ; extra == 'all'
Requires-Dist: humanize (==0.5.1) ; extra == 'all'
Requires-Dist: h2o-pysparkling-2.4 (==2.4.10) ; extra == 'all'
Requires-Dist: psutil (==5.7.2) ; extra == 'all'
Requires-Dist: backoff (==1.10.0) ; extra == 'all'
Requires-Dist: kombu (==4.6.1) ; extra == 'all'
Requires-Dist: pandas (==0.24.2) ; extra == 'all'
Requires-Dist: ordered-set (==3.1.1) ; extra == 'all'
Requires-Dist: deepdiff (==4.0.6) ; extra == 'all'
Requires-Dist: pypika (==0.32.0) ; extra == 'all'
Requires-Dist: statsmodels (==0.10.1) ; extra == 'all'
Requires-Dist: glom (==19.10.0) ; extra == 'all'
Requires-Dist: singleton-decorator (==1.0.0) ; extra == 'all'
Requires-Dist: nltk (==3.4.5) ; extra == 'all'
Requires-Dist: pytest ; extra == 'all'
Requires-Dist: mock ; extra == 'all'
Requires-Dist: nose ; extra == 'all'
Provides-Extra: docs
Requires-Dist: sphinx ; extra == 'docs'
Requires-Dist: pytest ; extra == 'docs'
Requires-Dist: mock ; extra == 'docs'
Requires-Dist: nose ; extra == 'docs'
Provides-Extra: lint
Requires-Dist: pep8 ; extra == 'lint'
Requires-Dist: pyflakes ; extra == 'lint'
Provides-Extra: test
Requires-Dist: pytest ; extra == 'test'
Requires-Dist: mock ; extra == 'test'
Requires-Dist: nose ; extra == 'test'
